MANIFEST.in
setup.cfg
setup.py
nayesdog/setup.py
nayesdog.egg-info/PKG-INFO
nayesdog.egg-info/SOURCES.txt
nayesdog.egg-info/dependency_links.txt
nayesdog.egg-info/entry_points.txt
nayesdog.egg-info/requires.txt
nayesdog.egg-info/top_level.txt