Metadata-Version: 1.1
Name: nayesdog
Version: 0.1.5
Summary: RSS reader with Naive Bayes powered recommendations
Home-page: http://github.com/MLdog/nayesdog
Author: Ilya Prokin, Sergio Peignier
Author-email: isprokin@gmail.com, sergio.peignier.zapata@gmail.com
License: UNKNOWN
Download-URL: https://github.com/MLdog/nayesdog/archive/v0.1.5.tar.gz
Keywords: RSS reader,Naive Bayes,recommendations
Platform: UNKNOWN
